datetime_parser/__init__.py
datetime_parser/parse_time.py
datetime_parser-1.1.0.dist-info/LICENSE
datetime_parser-1.1.0.dist-info/METADATA
datetime_parser-1.1.0.dist-info/WHEEL
datetime_parser-1.1.0.dist-info/top_level.txt
datetime_parser-1.1.0.dist-info/RECORD
