Metadata-Version: 2.1
Name: datetime-parser
Version: 1.1.0
Summary: Parse common datetime formats and a custom relative time format into a Pendulum object.
Home-page: https://github.com/swimlane/datetime-parser
Author: Swimlane
Author-email: info@swimlane.com
License: UNKNOWN
Project-URL: Bug Tracker, https://github.com/swimlane/datetime-parser/issues
Platform: UNKNOWN
Classifier: Programming Language :: Python :: 3
Classifier: License :: OSI Approved :: MIT License
Classifier: Operating System :: OS Independent
Requires-Python: >=3.6
License-File: LICENSE
Requires-Dist: pendulum (>=2.1.2)
